textcleaner/__init__.py
textcleaner/textcleaner.py
text_cleaner_fdelgados-2.0.1.dist-info/LICENSE
text_cleaner_fdelgados-2.0.1.dist-info/METADATA
text_cleaner_fdelgados-2.0.1.dist-info/WHEEL
text_cleaner_fdelgados-2.0.1.dist-info/top_level.txt
text_cleaner_fdelgados-2.0.1.dist-info/RECORD
