Metadata-Version: 2.1
Name: text-cleaner-fdelgados
Version: 2.0.1
Summary: Tools for cleaning and preprocessing text
Home-page: https://github.com/fdelgados/text-cleaner.git
Author: Cisco Delgado
Author-email: fdelgados@gmail.com
License: UNKNOWN
Platform: UNKNOWN
Requires-Python: >=3.8
License-File: LICENSE
Requires-Dist: beautifulsoup4 (==4.9.3)
Requires-Dist: Unidecode (==1.3.2)
